<?xml version="1.0" encoding="UTF-8"?>
<!DOCTYPE hibernate-mapping PUBLIC
        "-//Hibernate/Hibernate Configuration DTD 3.0//EN"
        "http://hibernate.org/dtd/hibernate-mapping-3.0.dtd">
<hibernate-mapping>
	<class name="com.techchefs.hibernateapp.dto.EmployeeDepartmentInfoBean" table="department_info">
		<id name="deptId" type="int">
			<column name="dept_id" />
		</id>
		
		<property name="deptName" type="java.lang.String">
			<column name="dept_name" />
		</property>
	
	</class>
</hibernate-mapping>